[
  {
    "name": "border-bottom-left-radius",
    "responsive": true,
    "responsive-pseudos": false,
    "extraSelector": "",
    "customProperties": [""],
    "pseudos": ["first"],
    "utilities": [
      {
        "class": "radius-bl-none",
        "properties": ["border-bottom-left-radius: 0;"]
      },
      {
        "class": "radius-bl-2xs",
        "properties": ["border-bottom-left-radius: 0.187rem;"]
      },
      {
        "class": "radius-bl-xs",
        "properties": ["border-bottom-left-radius: 0.25rem;"]
      },
      {
        "class": "radius-bl-sm",
        "properties": ["border-bottom-left-radius: 0.375rem;"]
      },
      {
        "class": "radius-bl-md",
        "properties": ["border-bottom-left-radius: 0.5rem;"]
      },
      {
        "class": "radius-bl-lg",
        "properties": ["border-bottom-left-radius: 0.75rem;"]
      },
      {
        "class": "radius-bl-xl",
        "properties": ["border-bottom-left-radius: 1rem;"]
      },
      {
        "class": "radius-bl-2xl",
        "properties": ["border-bottom-left-radius: 1.25rem;"]
      },
      {
        "class": "radius-bl-full",
        "properties": ["border-bottom-left-radius: 9999px;"]
      }
    ]
  },
  {
    "name": "border-bottom-right-radius",
    "responsive": true,
    "responsive-pseudos": false,
    "extraSelector": "",
    "customProperties": [""],
    "pseudos": ["last"],
    "utilities": [
      {
        "class": "radius-br-none",
        "properties": ["border-bottom-right-radius: 0;"]
      },
      {
        "class": "radius-br-2xs",
        "properties": ["border-bottom-right-radius: 0.187rem;"]
      },
      {
        "class": "radius-br-xs",
        "properties": ["border-bottom-right-radius: 0.25rem;"]
      },
      {
        "class": "radius-br-sm",
        "properties": ["border-bottom-right-radius: 0.375rem;"]
      },
      {
        "class": "radius-br-md",
        "properties": ["border-bottom-right-radius: 0.5rem;"]
      },
      {
        "class": "radius-br-lg",
        "properties": ["border-bottom-right-radius: 0.75rem;"]
      },
      {
        "class": "radius-br-xl",
        "properties": ["border-bottom-right-radius: 1rem;"]
      },
      {
        "class": "radius-br-2xl",
        "properties": ["border-bottom-right-radius: 1.25rem;"]
      },
      {
        "class": "radius-br-full",
        "properties": ["border-bottom-right-radius: 9999px;"]
      }
    ]
  },
  {
    "name": "border-bottom-width",
    "responsive": true,
    "responsive-pseudos": false,
    "extraSelector": "",
    "customProperties": [""],
    "pseudos": ["last"],
    "utilities": [
      {
        "class": "border-b-0",
        "properties": ["border-bottom-width: 0;"]
      },
      {
        "class": "border-b-2xs",
        "properties": ["border-bottom-width: 0.187rem;"]
      },
      {
        "class": "border-b-xs",
        "properties": ["border-bottom-width: 0.25rem;"]
      },
      {
        "class": "border-b-sm",
        "properties": ["border-bottom-width: 0.375rem;"]
      },
      {
        "class": "border-b-md",
        "properties": ["border-bottom-width: 0.5rem;"]
      },
      {
        "class": "border-b-lg",
        "properties": ["border-bottom-width: 0.75rem;"]
      },
      {
        "class": "border-b-xl",
        "properties": ["border-bottom-width: 1rem;"]
      },
      {
        "class": "border-b-2xl",
        "properties": ["border-bottom-width: 1.25rem;"]
      },
      {
        "class": "border-b-full",
        "properties": ["border-bottom-width: 9999px;"]
      }
    ]
  },
  {
    "name": "border-collapse",
    "responsive": false,
    "responsive-pseudos": false,
    "extraSelector": "",
    "customProperties": [""],
    "pseudos": [""],
    "utilities": [
      {
        "class": "border-separate",
        "properties": ["border-collapse: separate;"]
      },
      {
        "class": "border-collapse",
        "properties": ["border-collapse: colla[se;"]
      }
    ]
  },
  {
    "name": "border-color",
    "responsive": false,
    "responsive-pseudos": false,
    "extraSelector": "",
    "customProperties": [
      "--border-ltn: 50%",
      "--border-opacity: 1"
    ],
    "pseudos": ["hover", "group-hover", "focus", "dark"],
    "utilities": [
      {
        "class": "border-red",
        "properties": ["border-color: hsla(var(--red-hue), var(--red-sat), 100%, var(--border-opacity));"]
      },
      {
        "class": "border-orange",
        "properties": ["border-color: hsla(var(--orange-hue), var(--orange-sat), 100%, var(--border-opacity;))"]
      },
      {
        "class": "border-yellow",
        "properties": ["border-color: hsla(var(--yellow-hue), var(--yellow-sat), 100%, var(--border-opacity;))"]
      },
      {
        "class": "border-lemon",
        "properties": ["border-color: hsla(var(--lemon-hue), var(--lemon-sat), 100%, var(--border-opacity));"]
      },
      {
        "class": "border-olive",
        "properties": ["border-color: hsla(var(--olive-hue), var(--olive-sat), 100%, var(--border-opacity));"]
      },
      {
        "class": "border-lime",
        "properties": ["border-color: hsla(var(--lime-hue), var(--lime-sat), 100%, var(--border-opacity));"]
      },
      {
        "class": "border-green",
        "properties": ["border-color: hsla(var(--green-hue), var(--green-sat), 100%, var(--border-opacity));"]
      },
      {
        "class": "border-mint",
        "properties": ["border-color: hsla(var(--mint-hue), var(--mint-sat), 100%, var(--border-opacity));"]
      },
      {
        "class": "border-teal",
        "properties": ["border-color: hsla(var(--teal-hue), var(--teal-sat), 100%, var(--border-opacity));"]
      },
      {
        "class": "border-cyan",
        "properties": ["border-color: hsla(var(--cyan-hue), var(--cyan-sat), 100%, var(--border-opacity));"]
      },
      {
        "class": "border-sky",
        "properties": ["border-color: hsla(var(--sky-hue), var(--sky-sat), 100%, var(--border-opacity));"]
      },
      {
        "class": "border-blue",
        "properties": ["border-color: hsla(var(--blue-hue), var(--blue-sat), 100%, var(--border-opacity));"]
      },
      {
        "class": "border-indigo",
        "properties": ["border-color: hsla(var(--indigo-hue), var(--indigo-sat), 100%, var(--border-opacity);"]
      },
      {
        "class": "border-purple",
        "properties": ["border-color: hsla(var(--purple-hue), var(--purple-sat), 100%, var(--border-opacity));"]
      },
      {
        "class": "border-orchid",
        "properties": ["border-color: hsla(var(--orchid-hue), var(--orchid-sat), 100%, var(--border-opacity));"]
      },
      {
        "class": "border-magenta",
        "properties": ["border-color: hsla(var(--magenta-hue), var(--magenta-sat), 100%, var(--border-opacity));"]
      },
      {
        "class": "border-pink",
        "properties": ["border-color: hsla(var(--pink-hue), var(--pink-sat), 100%, var(--border-opacity));"]
      },
      {
        "class": "border-crimson",
        "properties": ["border-color: hsla(var(--crimson-hue), var(--crimson-sat), 100%, var(--border-opacity));"]
      },
      {
        "class": "border-white",
        "properties": ["border-color: hsla(var(--white-hue), var(--white-sat), 100%, var(--border-opacity));"]
      },
      {
        "class": "border-black",
        "properties": ["border-color: hsla(var(--black-hue), var(--black-sat), 100%, var(--border-opacity));"]
      },
      {
        "class": "border-cool-gray",
        "properties": ["border-color: hsla(var(--cool-gray-hue), var(--cool-gray-sat), 100%, var(--border-opacity));"]
      },
      {
        "class": "border-gray",
        "properties": ["border-color: hsla(var(--gray-hue), var(--gray-sat), 100%, var(--border-opacity));"]
      },
      {
        "class": "border-warm-gray",
        "properties": ["border-color: hsla(var(--warm-gray-hue), var(--warm-gray-sat), 100%, var(--border-opacity));"]
      },
      {
        "class": "border-transparent",
        "properties": ["border-color: transparent;"]
      },
      {
        "class": "border-current",
        "properties": ["border-color: current;"]
      }
    ]
  },
  {
    "name": "border-left-width",
    "responsive": true,
    "responsive-pseudos": false,
    "extraSelector": "",
    "customProperties": [""],
    "pseudos": ["first"],
    "utilities": [
      {
        "class": "",
        "properties": [""]
      }
    ]
  },
  {
    "name": "border-radius",
    "responsive": true,
    "responsive-pseudos": false,
    "extraSelector": "",
    "customProperties": [""],
    "pseudos": [""],
    "utilities": [
      {
        "class": "",
        "properties": [""]
      }
    ]
  },
  {
    "name": "border-right-width",
    "responsive": true,
    "responsive-pseudos": false,
    "extraSelector": "",
    "customProperties": [""],
    "pseudos": ["last"],
    "utilities": [
      {
        "class": "",
        "properties": [""]
      }
    ]
  },
  {
    "name": "border-style",
    "responsive": false,
    "responsive-pseudos": false,
    "extraSelector": "",
    "customProperties": [""],
    "pseudos": [""],
    "utilities": [
      {
        "class": "border-solid",
        "properties": ["border-style: solid;"]
      },
      {
        "class": "border-dashed",
        "properties": ["border-style: dashed;"]
      },
      {
        "class": "border-dotted",
        "properties": ["border-style: dotted;"]
      },
      {
        "class": "border-double",
        "properties": ["border-style: double;"]
      },
      {
        "class": "border-none",
        "properties": ["border-style: none;"]
      }
    ]
  },
  {
    "name": "border-top-left-radius",
    "responsive": true,
    "responsive-pseudos": false,
    "extraSelector": "",
    "customProperties": [""],
    "pseudos": ["first"],
    "utilities": [
      {
        "class": "",
        "properties": [""]
      }
    ]
  },
  {
    "name": "border-top-right-radius",
    "responsive": true,
    "responsive-pseudos": false,
    "extraSelector": "",
    "customProperties": [""],
    "pseudos": ["last"],
    "utilities": [
      {
        "class": "",
        "properties": [""]
      }
    ]
  },
  {
    "name": "border-top-width",
    "responsive": true,
    "responsive-pseudos": false,
    "extraSelector": "",
    "customProperties": [""],
    "pseudos": ["first"],
    "utilities": [
      {
        "class": "",
        "properties": [""]
      }
    ]
  },
  {
    "name": "border-width",
    "responsive": true,
    "responsive-pseudos": false,
    "extraSelector": "",
    "customProperties": [""],
    "pseudos": [""],
    "utilities": [
      {
        "class": "",
        "properties": [""]
      }
    ]
  },
  {
    "name": "border-bottom-radius",
    "responsive": true,
    "responsive-pseudos": false,
    "extraSelector": "",
    "customProperties": [""],
    "pseudos": ["last"],
    "utilities": [
      {
        "class": "",
        "properties": [""]
      }
    ]
  },
  {
    "name": "border-left-radius",
    "responsive": true,
    "responsive-pseudos": false,
    "extraSelector": "",
    "customProperties": [""],
    "pseudos": ["first"],
    "utilities": [
      {
        "class": "",
        "properties": [""]
      }
    ]
  },
  {
    "name": "border-right-radius",
    "responsive": true,
    "responsive-pseudos": false,
    "extraSelector": "",
    "customProperties": [""],
    "pseudos": ["last"],
    "utilities": [
      {
        "class": "",
        "properties": [""]
      }
    ]
  },
  {
    "name": "border-shade",
    "responsive": false,
    "responsive-pseudos": false,
    "extraSelector": "",
    "customProperties": [""],
    "pseudos": ["hover", "group-hover", "focus", "dark"],
    "utilities": [
      {
        "class": "",
        "properties": [""]
      }
    ]
  },
  {
    "name": "border-tint",
    "responsive": false,
    "responsive-pseudos": false,
    "extraSelector": "",
    "customProperties": [""],
    "pseudos": ["hover", "group-hover", "focus", "dark"],
    "utilities": [
      {
        "class": "",
        "properties": [""]
      }
    ]
  },
  {
    "name": "border-top-radius",
    "responsive": true,
    "responsive-pseudos": false,
    "extraSelector": "",
    "customProperties": [""],
    "pseudos": ["first"],
    "utilities": [
      {
        "class": "",
        "properties": [""]
      }
    ]
  }
]
